SeraphClicker/__init__.py
SeraphClicker/main.py
SeraphClicker/resources/Seraphelis-nobg.png
SeraphClicker-1.0.1.dist-info/LICENSE
SeraphClicker-1.0.1.dist-info/METADATA
SeraphClicker-1.0.1.dist-info/WHEEL
SeraphClicker-1.0.1.dist-info/entry_points.txt
SeraphClicker-1.0.1.dist-info/top_level.txt
SeraphClicker-1.0.1.dist-info/RECORD
