Metadata-Version: 2.1
Name: SeraphClicker
Version: 1.0.1
Summary: Just an autoclicker
Author: Hyaku
Classifier: Programming Language :: Python :: 3
Classifier: Programming Language :: Python :: 3.10
Classifier: Programming Language :: Python :: 3.11
Classifier: License :: OSI Approved :: MIT License
Classifier: Operating System :: OS Independent
Requires-Python: >=3.10
License-File: LICENSE
Requires-Dist: pyautogui
Requires-Dist: pynput
Requires-Dist: ttkthemes
